pydantic_db/__init__.py
pydantic_db/py.typed
pydantic_db-0.2.1.dist-info/METADATA
pydantic_db-0.2.1.dist-info/WHEEL
pydantic_db-0.2.1.dist-info/RECORD
