Metadata-Version: 2.4
Name: pydantic-db
Version: 0.2.1
Summary: SQL library agnostic data model framework
Project-URL: homepage, https://github.com/NRWLDev/pydantic-db
Author-email: Daniel Edgecombe <daniel@nrwl.co>
Maintainer-email: Daniel Edgecombe <daniel@nrwl.co>
License-Expression: Apache-2.0
Keywords: agnostic,database,model,pydantic
Classifier: Development Status :: 4 - Beta
Classifier: Environment :: Web Environment
Classifier: Intended Audience :: Developers
Classifier: License :: OSI Approved :: Apache Software License
Classifier: Operating System :: OS Independent
Classifier: Programming Language :: Python
Classifier: Programming Language :: Python :: 3
Classifier: Programming Language :: Python :: 3 :: Only
Classifier: Programming Language :: Python :: 3.10
Classifier: Programming Language :: Python :: 3.11
Classifier: Programming Language :: Python :: 3.12
Classifier: Programming Language :: Python :: 3.13
Classifier: Topic :: Database
Classifier: Topic :: Software Development
Classifier: Topic :: Utilities
Requires-Python: >=3.10
Requires-Dist: eval-type-backport>=0.2.2
Requires-Dist: pydantic>=2
Provides-Extra: dev
Requires-Dist: anys; extra == 'dev'
Requires-Dist: asyncpg>=0.29.0; extra == 'dev'
Requires-Dist: changelog-gen>=0.12; extra == 'dev'
Requires-Dist: dsnparse>=0.2.1; extra == 'dev'
Requires-Dist: mysql-connector-python>=9.3.0; extra == 'dev'
Requires-Dist: pre-commit>=3.0.2; extra == 'dev'
Requires-Dist: psycopg2>=2.9.10; extra == 'dev'
Requires-Dist: pytest-asyncio>=0.23.5; extra == 'dev'
Requires-Dist: pytest-cov>=4.1.0; extra == 'dev'
Requires-Dist: pytest-env>=0.8.1; extra == 'dev'
Requires-Dist: pytest-random-order>=1.1.1; extra == 'dev'
Requires-Dist: pytest>=8.0.2; extra == 'dev'
Requires-Dist: ruff>=0.6.4; extra == 'dev'
